metabook/__init__.py
metabook/__main__.py
metabook/cli.py
metabook/config.py
metabook/exceptions.py
metabook/metabook.py
metabook/metabook1.py
metabook/publishers.py
metabook-0.1.1.dist-info/LICENSE
metabook-0.1.1.dist-info/METADATA
metabook-0.1.1.dist-info/WHEEL
metabook-0.1.1.dist-info/entry_points.txt
metabook-0.1.1.dist-info/top_level.txt
metabook-0.1.1.dist-info/RECORD
