Metadata-Version: 2.1
Name: metabook
Version: 0.1.1
Summary: rename and organize your pdf book collection
Home-page: https://github.com/Stephen-RA-King/metabook
Download-URL: https://github.com/Stephen-RA-King/metabook/archive/refs/heads/main.zip
Author: Stephen R A King
Author-email: sking.github@gmail.com
Maintainer: Stephen R A King
Maintainer-email: sking.github@gmail.com
License: MIT
Project-URL: Bug Tracker, https://github.com/Stephen-RA-King/metabook/issues
Project-URL: CI, https://github.com/Stephen-RA-King/metabook/actions
Project-URL: Documentation, https://metabook.readthedocs.io/en/latest/
Project-URL: Release Notes, https://github.com/Stephen-RA-King/metabook/releases
Project-URL: Source Code, https://github.com/Stephen-RA-King/metabook/
Keywords: utility
Platform: Any
Classifier: Development Status :: 1 - Planning
Classifier: Environment :: Console
Classifier: Intended Audience :: Developers
Classifier: Operating System :: OS Independent
Classifier: Natural Language :: English
Classifier: Programming Language :: Python :: 3
Classifier: Programming Language :: Python :: 3 :: Only
Classifier: Programming Language :: Python :: 3.9
Classifier: Programming Language :: Python :: 3.10
Classifier: Programming Language :: Python :: 3.11
Classifier: Programming Language :: Python :: 3.12
Requires-Python: >=3.9
License-File: LICENSE
Requires-Dist: pdfplumber
Requires-Dist: requests
Requires-Dist: jinja2
Requires-Dist: pdfrw
Requires-Dist: PyPDF2
